mkdocs_expose_page_metadata/__init__.py
mkdocs_expose_page_metadata/helpers.py
mkdocs_expose_page_metadata/metadata.py
mkdocs_expose_page_metadata/metadata_page.py
mkdocs_expose_page_metadata/metadata_page_entry.py
mkdocs_expose_page_metadata/metadata_parser.py
mkdocs_expose_page_metadata/plugin.py
mkdocs_expose_page_metadata-1.1.6.dist-info/LICENSE
mkdocs_expose_page_metadata-1.1.6.dist-info/METADATA
mkdocs_expose_page_metadata-1.1.6.dist-info/WHEEL
mkdocs_expose_page_metadata-1.1.6.dist-info/entry_points.txt
mkdocs_expose_page_metadata-1.1.6.dist-info/top_level.txt
mkdocs_expose_page_metadata-1.1.6.dist-info/RECORD
