Metadata-Version: 2.1
Name: mkdocs-expose-page-metadata
Version: 1.1.6
Summary: This plug-in exposing all pages metadata in a single path!
Home-page: https://github.com/herberton/mkdocs-expose-page-metadata
Author: Herberton Candido Souza
Author-email: herberton@gmail.com
License: Apache-2.0
Keywords: mkdocs metadata
Requires-Python: >=3.9
License-File: LICENSE
Requires-Dist: mkdocs (>=1.1.2)
